{
  "id": "9e5d9315-f049-4e59-8b41-1b8bdcc9bad0",
  "prevId": "00000000-0000-0000-0000-000000000000",
  "version": "7",
  "dialect": "postgresql",
  "tables": {
    "public.pages": {
      "name": "pages",
      "schema": "",
      "columns": {
        "organization_id": {
          "name": "organization_id",
          "type": "varchar(191)",
          "primaryKey": false,
          "notNull": true
        },
        "id": {
          "name": "id",
          "type": "varchar(191)",
          "primaryKey": true,
          "notNull": true
        },
        "content": {
          "name": "content",
          "type": "text",
          "primaryKey": false,
          "notNull": false
        },
        "content_format": {
          "name": "content_format",
          "type": "integer",
          "primaryKey": false,
          "notNull": false
        },
        "course_id": {
          "name": "course_id",
          "type": "varchar(256)",
          "primaryKey": false,
          "notNull": false
        },
        "display": {
          "name": "display",
          "type": "integer",
          "primaryKey": false,
          "notNull": false
        },
        "display_options": {
          "name": "display_options",
          "type": "text",
          "primaryKey": false,
          "notNull": false
        },
        "intro": {
          "name": "intro",
          "type": "text",
          "primaryKey": false,
          "notNull": false
        },
        "intro_format": {
          "name": "intro_format",
          "type": "integer",
          "primaryKey": false,
          "notNull": false
        },
        "legacy_files": {
          "name": "legacy_files",
          "type": "integer",
          "primaryKey": false,
          "notNull": false
        },
        "legacy_files_last": {
          "name": "legacy_files_last",
          "type": "integer",
          "primaryKey": false,
          "notNull": false
        },
        "name": {
          "name": "name",
          "type": "varchar(256)",
          "primaryKey": false,
          "notNull": false
        },
        "revision": {
          "name": "revision",
          "type": "integer",
          "primaryKey": false,
          "notNull": false
        },
        "created_at": {
          "name": "created_at",
          "type": "timestamp",
          "primaryKey": false,
          "notNull": true,
          "default": "now()"
        },
        "updated_at": {
          "name": "updated_at",
          "type": "timestamp",
          "primaryKey": false,
          "notNull": true,
          "default": "now()"
        }
      },
      "indexes": {
        "course_id_idx": {
          "name": "course_id_idx",
          "columns": [
            {
              "expression": "course_id",
              "isExpression": false,
              "asc": true,
              "nulls": "last"
            }
          ],
          "isUnique": true,
          "concurrently": false,
          "method": "btree",
          "with": {}
        }
      },
      "foreignKeys": {},
      "compositePrimaryKeys": {},
      "uniqueConstraints": {}
    }
  },
  "enums": {},
  "schemas": {},
  "_meta": {
    "columns": {},
    "schemas": {},
    "tables": {}
  }
}